django_file_tools/__init__.py
django_file_tools/conf.py
django_file_tools/drf_views.py
django_file_tools/model_fields.py
django_file_tools/models.py
django_file_tools/pathers.py
django_file_tools/runner.py
django_file_tools/s3.py
django_file_tools/serializer_fields.py
django_file_tools/serializers.py
django_file_tools/storage_backends.py
django_file_tools/tests.py
django_file_tools/views.py
django_file_tools-0.1.7.dist-info/LICENSE
django_file_tools-0.1.7.dist-info/METADATA
django_file_tools-0.1.7.dist-info/WHEEL
django_file_tools-0.1.7.dist-info/RECORD
