Metadata-Version: 2.3
Name: django-file-tools
Version: 0.1.7
Summary: Tools for working with files in Django
License: MIT
Author: Enrico Barzetti
Requires-Python: >=3.9,<4.0
Classifier: License :: OSI Approved :: MIT License
Classifier: Programming Language :: Python :: 3
Classifier: Programming Language :: Python :: 3.9
Classifier: Programming Language :: Python :: 3.10
Classifier: Programming Language :: Python :: 3.11
Classifier: Programming Language :: Python :: 3.12
Classifier: Programming Language :: Python :: 3.13
Requires-Dist: boto3 (>=1.34.12,<2.0.0)
Requires-Dist: django (>=3.0)
Requires-Dist: django-environ (>=0.12.0,<0.13.0)
Requires-Dist: django-storages (>=1.14.6,<2.0.0)
Requires-Dist: djangorestframework (>=3.12.0,<4.0.0)
Project-URL: Homepage, https://github.com/enricobarzetti/django-file-tools
